imslib/__init__.py
imslib/_imslib.pyd
imslib/imslib.py
include/AcoustoOptics.h
include/Auxiliary.h
include/Compensation.h
include/ConnectionList.h
include/Containers.h
include/CS_ETH.h
include/CS_RS422.h
include/Diagnostics.h
include/FileSystem.h
include/FirmwareUpgrade.h
include/IBulkTransfer.h
include/IConnectionSettings.h
include/IEventHandler.h
include/Image.h
include/ImageOps.h
include/ImageProject.h
include/IMSSystem.h
include/IMSTypeDefs.h
include/LibVersion.h
include/SignalPath.h
include/SystemFunc.h
include/ToneBuffer.h
include/VCO.h
include/WaveShaping.h
imslib-2.0.6.dist-info/METADATA
imslib-2.0.6.dist-info/WHEEL
imslib-2.0.6.dist-info/RECORD
