Metadata-Version: 2.2
Name: imslib
Version: 2.0.6
Summary: Python bindings for iMS devices
Author-Email: Isomet Corporation <isomet@isomet.com>
License: MIT
Classifier: Programming Language :: Python :: 3
Classifier: Programming Language :: Python :: 3 :: Only
Classifier: Programming Language :: Python :: 3.8
Classifier: Programming Language :: Python :: 3.9
Classifier: Programming Language :: Python :: 3.10
Classifier: Programming Language :: Python :: 3.11
Classifier: Programming Language :: Python :: 3.12
Classifier: Programming Language :: Python :: 3.13
Classifier: Programming Language :: Python :: 3.14
Classifier: Programming Language :: Python :: Implementation :: CPython
Classifier: Programming Language :: C++
Project-URL: Homepage, https://github.com/Isomet-Corporation/imslib-python
Requires-Python: >=3.8
